Pytex_tools/__init__.py
Pytex_tools/variables.py
SD_Pytex_Tools-0.0.1.dist-info/METADATA
SD_Pytex_Tools-0.0.1.dist-info/WHEEL
SD_Pytex_Tools-0.0.1.dist-info/top_level.txt
SD_Pytex_Tools-0.0.1.dist-info/RECORD
